qontinui/__init__.py
qontinui/action_exceptions.py
qontinui/action_executors/__init__.py
qontinui/action_executors/base.py
qontinui/action_executors/control_flow.py
qontinui/action_executors/data_operations.py
qontinui/action_executors/delegating_executor.py
qontinui/action_executors/highlight_overlay.py
qontinui/action_executors/keyboard.py
qontinui/action_executors/mouse.py
qontinui/action_executors/navigation.py
qontinui/action_executors/pattern_builder.py
qontinui/action_executors/pattern_loader.py
qontinui/action_executors/registry.py
qontinui/action_executors/target_resolver.py
qontinui/action_executors/template_match_engine.py
qontinui/action_executors/utility.py
qontinui/action_executors/vision.py
qontinui/actions/__init__.py
qontinui/actions/action.py
qontinui/actions/action_chain_options.py
qontinui/actions/action_config.py
qontinui/actions/action_execution.py
qontinui/actions/action_interface.py
qontinui/actions/action_options.py
qontinui/actions/action_result.py
qontinui/actions/action_service.py
qontinui/actions/action_type.py
qontinui/actions/actions.py
qontinui/actions/adapter_impl/__init__.py
qontinui/actions/adapter_impl/adapter_result.py
qontinui/actions/adapter_impl/keyboard_adapter.py
qontinui/actions/adapter_impl/mouse_adapter.py
qontinui/actions/adapter_impl/screen_adapter.py
qontinui/actions/adapters.py
qontinui/actions/basic/__init__.py
qontinui/actions/basic/click/__init__.py
qontinui/actions/basic/click/click.py
qontinui/actions/basic/click/click_options.py
qontinui/actions/basic/click/mouse_press_options.py
qontinui/actions/basic/color/__init__.py
qontinui/actions/basic/color/classify.py
qontinui/actions/basic/color/color_cluster.py
qontinui/actions/basic/color/color_find_options.py
qontinui/actions/basic/color/color_matcher.py
qontinui/actions/basic/color/color_profile.py
qontinui/actions/basic/color/color_statistics.py
qontinui/actions/basic/color/find_color.py
qontinui/actions/basic/color/find_color_orchestrator.py
qontinui-0.1.1.dist-info/entry_points.txt
qontinui-0.1.1.dist-info/licenses/LICENSE
qontinui-0.1.1.dist-info/METADATA
qontinui-0.1.1.dist-info/WHEEL
qontinui-0.1.1.dist-info/RECORD
