Metadata-Version: 2.4
Name: qontinui
Version: 0.1.1
Summary: Model-based GUI automation with AI-enhanced perception
License: MIT
License-File: LICENSE
Keywords: gui,automation,ai,testing,rpa
Author: Joshua Spinak
Author-email: jspinak@alum.mit.edu
Requires-Python: >=3.12,<4.0
Classifier: Development Status :: 3 - Alpha
Classifier: Intended Audience :: Developers
Classifier: License :: OSI Approved :: MIT License
Classifier: Programming Language :: Python :: 3
Classifier: Programming Language :: Python :: 3.12
Classifier: Programming Language :: Python :: 3.13
Classifier: Programming Language :: Python :: 3.14
Classifier: Topic :: Software Development :: Libraries :: Python Modules
Classifier: Topic :: Software Development :: Testing
Provides-Extra: all
Provides-Extra: sam
Requires-Dist: accelerate (>=0.25,<0.26)
Requires-Dist: croniter (>=5.0,<6.0)
Requires-Dist: easyocr (>=1.7,<2.0)
Requires-Dist: faiss-cpu (>=1.7,<2.0)
Requires-Dist: lark (>=1.1,<2.0)
Requires-Dist: mss (>=9.0,<10.0)
Requires-Dist: networkx (>=3.2,<4.0)
Requires-Dist: numpy (>=1.26,<2.0)
Requires-Dist: opencv-python-headless (>=4.9,<5.0)
Requires-Dist: pillow (>=10.2,<11.0)
Requires-Dist: prometheus-client (>=0.19,<0.20)
Requires-Dist: psutil (>=5.9,<6.0)
Requires-Dist: pydantic (>=2.11.9,<3.0.0)
Requires-Dist: pydantic-settings (>=2.0,<3.0)
Requires-Dist: pynput (>=1.7,<2.0)
Requires-Dist: python-dotenv (>=1.0,<2.0)
Requires-Dist: scikit-learn (>=1.3,<2.0)
Requires-Dist: segment-anything (>=1.0,<2.0) ; extra == "sam" or extra == "all"
Requires-Dist: sqlalchemy (>=2.0,<3.0)
Requires-Dist: structlog (>=24.0,<25.0)
Requires-Dist: supervision (>=0.26,<0.27)
Requires-Dist: timm (>=0.9,<0.10)
Requires-Dist: tokenizers (>=0.15,<0.16)
Requires-Dist: torch (>=2.2,<3.0)
Requires-Dist: torchvision (>=0.17)
Requires-Dist: transformers (>=4.36,<5.0)
Requires-Dist: transitions (>=0.9,<0.10)
Requires-Dist: ultralytics (>=8.0,<9.0)
Project-URL: Documentation, https://qontinui.github.io
Project-URL: Homepage, https://github.com/qontinui/qontinui
Project-URL: Repository, https://github.com/qontinui/qontinui
